[
  {
    "heading": "",
    "items": [
      {
        "title": "Introduction",
        "href": "/docs/getting-started/introduction/"
      },
      {
        "title": "Quick Start",
        "href": "/docs/getting-started/quick-start/"
      },
      {
        "title": "Key Concepts",
        "href": "/docs/getting-started/key-concepts/"
      },
      {
        "title": "Accounts & Workspaces",
        "href": "/docs/getting-started/accounts-workspaces/"
      },
      {
        "title": "Onboarding & First Steps",
        "href": "/docs/getting-started/onboarding-first-steps/"
      },
      {
        "title": "Troubleshooting Setup",
        "href": "/docs/getting-started/troubleshooting-setup/"
      }
    ]
  },
  {
    "heading": "",
    "items": [
      {
        "title": "The content engine",
        "href": "/docs/how-it-works/content-engine/"
      },
      {
        "title": "How the AI works",
        "href": "/docs/how-it-works/how-the-ai-works/"
      },
      {
        "title": "Quality & safety",
        "href": "/docs/how-it-works/quality-safety/"
      },
      {
        "title": "AI Models & Generation Pipeline",
        "href": "/docs/how-it-works/ai-models-and-pipeline/"
      }
    ]
  },
  {
    "heading": "",
    "items": [
      {
        "title": "Overview",
        "href": "/docs/content-seo/overview/"
      },
      {
        "title": "Business Setup",
        "href": "/docs/content-seo/business-setup/"
      },
      {
        "title": "Content Plans & Keywords",
        "href": "/docs/content-seo/content-plans/"
      },
      {
        "title": "Blog Generation",
        "href": "/docs/content-seo/blog-generation/"
      },
      {
        "title": "Publishing",
        "href": "/docs/content-seo/publishing/"
      },
      {
        "title": "Preferences",
        "href": "/docs/content-seo/preferences/"
      },
      {
        "title": "Connect Platforms",
        "href": "/docs/content-seo/connect-platforms/"
      },
      {
        "title": "AI Error Recovery & Retries",
        "href": "/docs/content-seo/ai-error-recovery/"
      },
      {
        "title": "Automated Generation (Cron)",
        "href": "/docs/content-seo/automated-generation/"
      },
      {
        "title": "Blog Status Lifecycle",
        "href": "/docs/content-seo/blog-status-lifecycle/"
      },
      {
        "title": "Blog Type Options",
        "href": "/docs/content-seo/blog-types/"
      },
      {
        "title": "Competitors & Audiences",
        "href": "/docs/content-seo/competitors-audiences/"
      },
      {
        "title": "Compliance Profiles",
        "href": "/docs/content-seo/compliance-profiles/"
      },
      {
        "title": "AI Content Safety & Integrity Guardrails",
        "href": "/docs/content-seo/content-safety-guardrails/"
      },
      {
        "title": "Draft & Approval Workflow",
        "href": "/docs/content-seo/draft-approval-workflow/"
      },
      {
        "title": "Generate More & Bonus Blogs",
        "href": "/docs/content-seo/generate-more-bonus-blogs/"
      },
      {
        "title": "Image Generation",
        "href": "/docs/content-seo/image-generation/"
      },
      {
        "title": "Internal Linking",
        "href": "/docs/content-seo/internal-linking/"
      },
      {
        "title": "Keyword Strategy & Rotation",
        "href": "/docs/content-seo/keyword-strategy-rotation/"
      },
      {
        "title": "Promotions Calendar",
        "href": "/docs/content-seo/promotions-calendar/"
      },
      {
        "title": "Publishing Errors & Retries",
        "href": "/docs/content-seo/publishing-errors/"
      },
      {
        "title": "Publishing Modes & Autopilot",
        "href": "/docs/content-seo/publishing-modes/"
      },
      {
        "title": "Quota & Limits",
        "href": "/docs/content-seo/quota-and-limits/"
      },
      {
        "title": "Regenerating Content",
        "href": "/docs/content-seo/regenerating-content/"
      },
      {
        "title": "Time-Based Scheduling & Missed Posts",
        "href": "/docs/content-seo/scheduling-missed-posts/"
      },
      {
        "title": "SEO Scoring Explained",
        "href": "/docs/content-seo/seo-scoring/"
      },
      {
        "title": "Sources & Brand Voice",
        "href": "/docs/content-seo/sources-brand-voice/"
      },
      {
        "title": "User Direction",
        "href": "/docs/content-seo/user-direction/"
      },
      {
        "title": "Word Count & Targets",
        "href": "/docs/content-seo/word-count-targets/"
      }
    ]
  },
  {
    "heading": "",
    "items": [
      {
        "title": "Overview",
        "href": "/docs/local-seo/overview/"
      },
      {
        "title": "Google Business Profile",
        "href": "/docs/local-seo/google-business-profile/"
      },
      {
        "title": "Reviews",
        "href": "/docs/local-seo/reviews/"
      },
      {
        "title": "Advertising Compliance & Validation",
        "href": "/docs/local-seo/advertising-compliance/"
      },
      {
        "title": "Content Plan Management",
        "href": "/docs/local-seo/content-plan-management/"
      },
      {
        "title": "Data Sync & Status",
        "href": "/docs/local-seo/data-sync/"
      },
      {
        "title": "Error Handling & Sync Failures",
        "href": "/docs/local-seo/error-handling-sync-failures/"
      },
      {
        "title": "GBP Posts & Content Calendar",
        "href": "/docs/local-seo/gbp-posts-calendar/"
      },
      {
        "title": "Industry Presets & Brand Intake",
        "href": "/docs/local-seo/industry-presets-brand-intake/"
      },
      {
        "title": "Keywords & Local Rankings",
        "href": "/docs/local-seo/keywords-local-rankings/"
      },
      {
        "title": "Multi-Project & Shared Access",
        "href": "/docs/local-seo/local-seo-shared-access/"
      },
      {
        "title": "Locations & Business Details",
        "href": "/docs/local-seo/locations-business-details/"
      },
      {
        "title": "Onboarding & Business Setup",
        "href": "/docs/local-seo/onboarding-business-setup/"
      },
      {
        "title": "Subscription, Trials & Limits",
        "href": "/docs/local-seo/subscription-trials-limits/"
      }
    ]
  },
  {
    "heading": "",
    "items": [
      {
        "title": "Overview",
        "href": "/docs/social-media/overview/"
      },
      {
        "title": "Connecting Platforms",
        "href": "/docs/social-media/connecting-platforms/"
      },
      {
        "title": "Brand & Style",
        "href": "/docs/social-media/brand-style/"
      },
      {
        "title": "Content & Scheduling",
        "href": "/docs/social-media/content-scheduling/"
      },
      {
        "title": "Approval & Review Workflow",
        "href": "/docs/social-media/approval-review-workflow/"
      },
      {
        "title": "Connection Management & Sync",
        "href": "/docs/social-media/connection-management-sync/"
      },
      {
        "title": "Content Plans & Generation",
        "href": "/docs/social-media/content-plans-generation/"
      },
      {
        "title": "Content Preferences & Pillars",
        "href": "/docs/social-media/content-preferences-pillars/"
      },
      {
        "title": "Platform Character Limits",
        "href": "/docs/social-media/platform-character-limits/"
      },
      {
        "title": "Post Customization",
        "href": "/docs/social-media/post-customization/"
      },
      {
        "title": "Post Deletion & Unpublishing",
        "href": "/docs/social-media/post-deletion/"
      },
      {
        "title": "Post Quota & Limits",
        "href": "/docs/social-media/post-quota-limits/"
      },
      {
        "title": "Post States & Failures",
        "href": "/docs/social-media/post-states-failures/"
      },
      {
        "title": "Publishing & Scheduling",
        "href": "/docs/social-media/publishing-scheduling/"
      },
      {
        "title": "Repurpose from Blog",
        "href": "/docs/social-media/repurpose-from-blog/"
      },
      {
        "title": "Website Auto-Extraction & Asset Uploads",
        "href": "/docs/social-media/website-extraction-assets/"
      }
    ]
  },
  {
    "heading": "",
    "items": [
      {
        "title": "Workspace & Team",
        "href": "/docs/account/workspace-team/"
      },
      {
        "title": "Billing & Plans",
        "href": "/docs/account/billing/"
      },
      {
        "title": "Add-ons & Managed Services",
        "href": "/docs/account/addons-managed-services/"
      },
      {
        "title": "Payments, Invoices & Payment Methods",
        "href": "/docs/account/payments-invoices/"
      },
      {
        "title": "Plans & Pricing Reference",
        "href": "/docs/account/plans-pricing/"
      },
      {
        "title": "Subscription Status & Access",
        "href": "/docs/account/subscription-status-access/"
      },
      {
        "title": "Trials Explained",
        "href": "/docs/account/trials-explained/"
      }
    ]
  },
  {
    "heading": "",
    "items": [
      {
        "title": "Public Blog API",
        "href": "/docs/developers/public-blog-api/"
      },
      {
        "title": "Static Site Integration",
        "href": "/docs/developers/static-site-integration/"
      },
      {
        "title": "Deploy Hooks",
        "href": "/docs/developers/deploy-hooks/"
      },
      {
        "title": "Webhook Reference",
        "href": "/docs/developers/webhook-reference/"
      },
      {
        "title": "Agent Keys & MCP Server",
        "href": "/docs/developers/agent-keys-mcp/"
      },
      {
        "title": "MCP Tools Reference",
        "href": "/docs/developers/mcp-tools-reference/"
      }
    ]
  }
]