{
  "chunk": "/home/ritik/thestacc.com-astro/thestacc-2026-site/Stacc/blog-migration/small-chunks/chunk-003.txt",
  "total": 27,
  "completed": [
    "fanout-queries-strategy",
    "financial-advisor-seo-guide",
    "find-content-gaps",
    "find-low-competition-keywords",
    "fix-broken-links",
    "fix-keyword-cannibalization",
    "fix-thin-content",
    "florist-seo-guide",
    "format-blog-post",
    "forum-presence-ai-visibility",
    "forum-submission-sites-list",
    "framer-seo-guide",
    "free-tool-ideas-link-building",
    "free-tools-traffic-case-study",
    "freshness-signals-ai-search",
    "ftc-ai-disclosure-rules-2026",
    "funeral-home-seo-guide",
    "future-ai-writing",
    "gbp-ai-era-guide",
    "gbp-ai-review-summaries",
    "gbp-categories-guide",
    "gbp-data-ai-answers",
    "gbp-engagement-metrics-ranking",
    "gbp-optimization-ai-mode",
    "gbp-photos-guide",
    "gbp-posting-frequency",
    "gbp-services-guide"
  ],
  "failed": {},
  "skipped_already_done": []
}